[{"badgeClass": "info", "title": "Army Air Field", "image": "army-air-field.jpg"},{"badgeClass": "info", "title": "River Guides", "image": "river-guides.jpg"},{"badgeClass": "info", "title": "Thorwald Hanson", "image": "thorwald-hanson.jpg"},{"badgeClass": "info", "title": "Mercy Hospital", "image": "mercy-hospital.jpg"},{"badgeClass": "info", "title": "Stephan Family", "image": "stephan-family.jpg"},{"badgeClass": "info", "title": "Old Court House", "image": "old-court-house.jpg"},{"badgeClass": "info", "title": "Skingley House", "image": "skingley-house.jpg"},{"badgeClass": "info", "title": "Grayling Machine Shop 1", "image": "grayling-machine-shop-1.jpg"},{"badgeClass": "info", "title": "Grayling Machine Shop 2", "image": "grayling-machine-shop-2.jpg"},{"badgeClass": "info", "title": "Grayling House", "image": "grayling-house.jpg"},{"badgeClass": "info", "title": "Chief Daughter", "image": "chief-daughter.jpg"},{"badgeClass": "info", "title": "Hanson Salling Mill", "image": "hanson-salling-mill.jpg"},{"badgeClass": "info", "title": "Band Mill", "image": "band-mill.jpg"},{"badgeClass": "info", "title": "Temple Theater", "image": "temple-theater.jpg"},{"badgeClass": "info", "title": "Boiler Explosion", "image": "boiler-explosion.jpg"},{"badgeClass": "info", "title": "Methodist Church", "image": "methodist-church.jpg"},{"badgeClass": "info", "title": "Manistee Northeast Rr Depot", "image": "manistee-northeast-rr-depot.jpg"},{"badgeClass": "info", "title": "Railroad Construction", "image": "railroad-construction.jpg"},{"badgeClass": "info", "title": "Railroad Inspection", "image": "railroad-inspection.jpg"},{"badgeClass": "info", "title": "Mng Review", "image": "mng-review.jpg"},{"badgeClass": "info", "title": "Mill Center Yard", "image": "mill-center-yard.jpg"},{"badgeClass": "info", "title": "Mc Rr Yard", "image": "mc-rr-yard.jpg"},{"badgeClass": "info", "title": "Dupont Ave", "image": "dupont-ave.jpg"},{"badgeClass": "info", "title": "South Side School", "image": "south-side-school.jpg"},{"badgeClass": "info", "title": "Michigan Avenue", "image": "michigan-avenue.jpg"},{"badgeClass": "info", "title": "Praire Pike", "image": "praire-pike.jpg"},{"badgeClass": "info", "title": "Roy Lovely", "image": "roy-lovely.jpg"},{"badgeClass": "info", "title": "Pump House", "image": "pump-house.jpg"},{"badgeClass": "info", "title": "Stephan Bridge", "image": "stephan-bridge.jpg"},{"badgeClass": "info", "title": "Chase Bridge", "image": "chase-bridge.jpg"},{"badgeClass": "info", "title": "Grayling Aerial View", "image": "grayling-aerial-view.jpg"},{"badgeClass": "info", "title": "Pickle Factory", "image": "pickle-factory.jpg"},{"badgeClass": "info", "title": "Camp Grayling", "image": "camp-grayling.jpg"},{"badgeClass": "info", "title": "Citizens Band", "image": "citizens-band.jpg"},{"badgeClass": "info", "title": "Citizens Band 2", "image": "citizens-band-2.jpg"},{"badgeClass": "info", "title": "Ice Harvest", "image": "ice-harvest.jpg"},{"badgeClass": "info", "title": "Camp Abbey", "image": "camp-abbey.jpg"},{"badgeClass": "info", "title": "Camp Grayling 2", "image": "camp-grayling-2.jpg"},{"badgeClass": "info", "title": "Cedar Street", "image": "cedar-street.jpg"},{"badgeClass": "info", "title": "Grayling Mi 1875", "image": "grayling-mi-1875.jpg"},{"badgeClass": "info", "title": "George Mason", "image": "george-mason.jpg"},{"badgeClass": "info", "title": "Old Railroad Depot", "image": "old-railroad-depot.jpg"},{"badgeClass": "info", "title": "Dupont Plant", "image": "dupont-plant.jpg"},{"badgeClass": "info", "title": "Opera House", "image": "opera-house.jpg"},{"badgeClass": "info", "title": "Notch", "image": "notch.jpg"},{"badgeClass": "info", "title": "Court House 1", "image": "court-house-1.jpg"},{"badgeClass": "info", "title": "Court House 2", "image": "court-house-2.jpg"},{"badgeClass": "info", "title": "Michigan Avenue 2", "image": "michigan-avenue-2.jpg"},{"badgeClass": "info", "title": "Danish Church", "image": "danish-church.jpg"},{"badgeClass": "info", "title": "Danebod Hall", "image": "danebod-hall.jpg"},{"badgeClass": "info", "title": "Hanson Home", "image": "hanson-home.jpg"},{"badgeClass": "info", "title": "Michigan Avenue 3", "image": "michigan-avenue-3.jpg"},{"badgeClass": "info", "title": "Snow Roller", "image": "snow-roller.jpg"},{"badgeClass": "info", "title": "Public Park", "image": "public-park.jpg"},{"badgeClass": "info", "title": "Michelson House", "image": "michelson-house.jpg"},{"badgeClass": "info", "title": "Sorenson Store", "image": "sorenson-store.jpg"},{"badgeClass": "info", "title": "Train At Depot", "image": "train-at-depot.jpg"},{"badgeClass": "info", "title": "Rube Babbitt", "image": "rube-babbitt.jpg"},{"badgeClass": "info", "title": "Electric Light Dam", "image": "electric-light-dam.jpg"},{"badgeClass": "info", "title": "Grayling School", "image": "grayling-school.jpg"},{"badgeClass": "info", "title": "Grayling School Fire", "image": "grayling-school-fire.jpg"},{"badgeClass": "info", "title": "South Side Church", "image": "south-side-church.jpg"},{"badgeClass": "info", "title": "Fish Hatchery 1", "image": "fish-hatchery-1.jpg"},{"badgeClass": "info", "title": "Fish Hatchery 2", "image": "fish-hatchery-2.jpg"},{"badgeClass": "info", "title": "Fish Hatchery 3", "image": "fish-hatchery-3.jpg"},{"badgeClass": "info", "title": "Hatchery Ponds", "image": "hatchery-ponds.jpg"},{"badgeClass": "info", "title": "Fish Hatchery Aerial", "image": "fish-hatchery-aerial.jpg"},{"badgeClass": "info", "title": "Fish Hatchery Aerial 2", "image": "fish-hatchery-aerial-2.jpg"},{"badgeClass": "info", "title": "Fish Hatchery 1950", "image": "fish-hatchery-1950.jpg"},{"badgeClass": "info", "title": "Fish Hatchery 1952", "image": "fish-hatchery-1952.jpg"},{"badgeClass": "info", "title": "Fish Hatchery 1914", "image": "fish-hatchery-1914.jpg"},{"badgeClass": "info", "title": "Suspension Bridge", "image": "suspension-bridge.jpg"},{"badgeClass": "info", "title": "Browns Restaurant", "image": "browns-restaurant.jpg"},{"badgeClass": "info", "title": "Marching Band", "image": "marching-band.jpg"}]